odoo/addons/product_category_type/README.rst
odoo/addons/product_category_type/__init__.py
odoo/addons/product_category_type/__manifest__.py
odoo/addons/product_category_type/demo/product_category.xml
odoo/addons/product_category_type/i18n/de.po
odoo/addons/product_category_type/i18n/es.po
odoo/addons/product_category_type/i18n/fr.po
odoo/addons/product_category_type/i18n/hr.po
odoo/addons/product_category_type/i18n/it.po
odoo/addons/product_category_type/i18n/product_category_type.pot
odoo/addons/product_category_type/models/__init__.py
odoo/addons/product_category_type/models/product_category.py
odoo/addons/product_category_type/models/product_template.py
odoo/addons/product_category_type/readme/CONTRIBUTORS.md
odoo/addons/product_category_type/readme/DESCRIPTION.md
odoo/addons/product_category_type/static/description/icon.png
odoo/addons/product_category_type/static/description/index.html
odoo/addons/product_category_type/static/description/product_category_tree.png
odoo/addons/product_category_type/static/description/product_template_form.png
odoo/addons/product_category_type/views/product_category.xml
odoo_addon_product_category_type-18.0.1.0.0.2.dist-info/METADATA
odoo_addon_product_category_type-18.0.1.0.0.2.dist-info/WHEEL
odoo_addon_product_category_type-18.0.1.0.0.2.dist-info/top_level.txt
odoo_addon_product_category_type-18.0.1.0.0.2.dist-info/RECORD
